{"lastUsed":1632519929153,"path":"E:\/AmitGrad","projectCount":2,"recentFiles":[{"path":"\/Control_MC","parentWorkspace":"E:\/AmitGrad","name":"application.c","lastModified":1632519943342,"locationURI":"file:\/E:\/AmitGrad\/Control_MC\/application.c"},{"path":"\/Sink_MC","parentWorkspace":"E:\/AmitGrad","name":"SPI_program.c","lastModified":1632430012145,"locationURI":"file:\/E:\/AmitGrad\/Sink_MC\/SPI_program.c"},{"path":"\/Sink_MC","parentWorkspace":"E:\/AmitGrad","name":"ACTUATOR_config.h","lastModified":1632427178817,"locationURI":"file:\/E:\/AmitGrad\/Sink_MC\/ACTUATOR_config.h"},{"path":"\/Control_MC","parentWorkspace":"E:\/AmitGrad","name":"PORT_config.h","lastModified":1632430067244,"locationURI":"file:\/E:\/AmitGrad\/Control_MC\/PORT_config.h"},{"path":"\/Sink_MC","parentWorkspace":"E:\/AmitGrad","name":"SPI_private.h","lastModified":1632429562319,"locationURI":"file:\/E:\/AmitGrad\/Sink_MC\/SPI_private.h"},{"path":"\/Sink_MC","parentWorkspace":"E:\/AmitGrad","name":"SPI_interface.h","lastModified":1632519123756,"locationURI":"file:\/E:\/AmitGrad\/Sink_MC\/SPI_interface.h"},{"path":"\/Control_MC","parentWorkspace":"E:\/AmitGrad","name":"BluetoothModule.c","lastModified":1632519511097,"locationURI":"file:\/E:\/AmitGrad\/Control_MC\/BluetoothModule.c"},{"path":"\/Sink_MC","parentWorkspace":"E:\/AmitGrad","name":"application.c","lastModified":1632519129588,"locationURI":"file:\/E:\/AmitGrad\/Sink_MC\/application.c"},{"path":"\/Sink_MC","parentWorkspace":"E:\/AmitGrad","name":"DIO_interface.h","lastModified":1632427284274,"locationURI":"file:\/E:\/AmitGrad\/Sink_MC\/DIO_interface.h"},{"path":"\/Sink_MC","parentWorkspace":"E:\/AmitGrad","name":"CommunicationLinker.h","lastModified":1632518858779,"locationURI":"file:\/E:\/AmitGrad\/Sink_MC\/CommunicationLinker.h"},{"path":"\/Sink_MC","parentWorkspace":"E:\/AmitGrad","name":"PORT_config.h","lastModified":1632430083475,"locationURI":"file:\/E:\/AmitGrad\/Sink_MC\/PORT_config.h"},{"path":"\/Control_MC","parentWorkspace":"E:\/AmitGrad","name":"SPI_program.c","lastModified":1632429190379,"locationURI":"file:\/E:\/AmitGrad\/Control_MC\/SPI_program.c"},{"path":"\/Sink_MC","parentWorkspace":"E:\/AmitGrad","name":"DIO_program.c","lastModified":1632428876802,"locationURI":"file:\/E:\/AmitGrad\/Sink_MC\/DIO_program.c"},{"path":"\/Sink_MC","parentWorkspace":"E:\/AmitGrad","name":"ACTUATOR_program.c","lastModified":1632428219176,"locationURI":"file:\/E:\/AmitGrad\/Sink_MC\/ACTUATOR_program.c"},{"path":"\/Sink_MC","parentWorkspace":"E:\/AmitGrad","name":"ACTUATOR_interface.h","lastModified":1632430449339,"locationURI":"file:\/E:\/AmitGrad\/Sink_MC\/ACTUATOR_interface.h"},{"path":"\/Control_MC","parentWorkspace":"E:\/AmitGrad","name":"BluetoothModule.h","lastModified":1632519943342,"locationURI":"file:\/E:\/AmitGrad\/Control_MC\/BluetoothModule.h"},{"path":"\/Control_MC","parentWorkspace":"E:\/AmitGrad","name":"UART_interface.h","lastModified":1632519508966,"locationURI":"file:\/E:\/AmitGrad\/Control_MC\/UART_interface.h"},{"path":"\/Control_MC","parentWorkspace":"E:\/AmitGrad","name":"UART_program.c","lastModified":1632361345777,"locationURI":"file:\/E:\/AmitGrad\/Control_MC\/UART_program.c"},{"path":"\/Control_MC","parentWorkspace":"E:\/AmitGrad","name":"SPI_interface.h","lastModified":1632429724215,"locationURI":"file:\/E:\/AmitGrad\/Control_MC\/SPI_interface.h"},{"path":"\/Sink_MC","parentWorkspace":"E:\/AmitGrad","name":"CommunicationLinker.c","lastModified":1632519129588,"locationURI":"file:\/E:\/AmitGrad\/Sink_MC\/CommunicationLinker.c"}]}